setup.py
twisted_cql/__init__.py
twisted_cql/session.py
twisted_cql.egg-info/PKG-INFO
twisted_cql.egg-info/SOURCES.txt
twisted_cql.egg-info/dependency_links.txt
twisted_cql.egg-info/not-zip-safe
twisted_cql.egg-info/pbr.json
twisted_cql.egg-info/requires.txt
twisted_cql.egg-info/top_level.txt