Metadata-Version: 1.0
Name: twisted-cql
Version: 0.5.8
Summary: Twisted CQL client.
Home-page: https://github.com/williamsjj/twisted_cql
Author: DigiTar
Author-email: support@digitar.com
License: BSD Simplified
Keywords: twisted cql cassandra datastax
Platform: UNKNOWN
